MANIFEST.in
README.rst
buildout.cfg
requirements.txt
setup.py
version.txt
bob/__init__.py
bob.ip.skincolorfilter.egg-info/PKG-INFO
bob.ip.skincolorfilter.egg-info/SOURCES.txt
bob.ip.skincolorfilter.egg-info/dependency_links.txt
bob.ip.skincolorfilter.egg-info/requires.txt
bob.ip.skincolorfilter.egg-info/top_level.txt
bob/ip/__init__.py
bob/ip/skincolorfilter/__init__.py
bob/ip/skincolorfilter/data/test-face.jpg
bob/ip/skincolorfilter/script/__init__.py
bob/ip/skincolorfilter/script/test.py
doc/conf.py
doc/guide.rst
doc/index.rst
doc/py_api.rst
doc/img/favicon.ico
doc/img/logo.png
doc/pyplots/detect_skin_pixels.py