Metadata-Version: 1.1
Name: bob.ip.skincolorfilter
Version: 0.0.4
Summary: Skin color filter in the rg colorspace
Home-page: https://www.gitlab.idiap.ch/bob/bob.ip.skincolorfilter
Author: Guillaume Heusch
Author-email: guillaume.heusch@idiap.ch
License: BSD
Keywords: bob
Platform: UNKNOWN
Classifier: Framework :: Bob
Classifier: Development Status :: 3 - Alpha
Classifier: Intended Audience :: Developers
Classifier: License :: OSI Approved :: BSD License
Classifier: Natural Language :: English
Classifier: Programming Language :: Python
